{"lifecycle":[{"cells":[{"type":"fsa.StartState","size":{"width":20,"height":20},"position":{"x":150,"y":255},"angle":0,"id":"450f4811-fb2e-4296-83f8-b282f872a957","z":1,"attrs":{}},{"type":"fsa.Arrow","smooth":true,"source":{"id":"450f4811-fb2e-4296-83f8-b282f872a957"},"target":{"id":"9b9eab5d-10c5-4b81-86ff-454c77f7ced2"},"labels":[{"position":0.5,"attrs":{"text":{"text":"openAccount","font-weight":"bold"}}}],"code":"event openAccount[minimalDeposit: Money = EUR 0.00]\n (accountNumber: IBAN, initialDeposit : Money) {\n\n preconditions {\n initialDeposit >= minimalDeposit;\n }\n\n postconditions {\n new this.balance == initialDeposit;\n new this.accountNumber == accountNumber;\n }\n }","id":"bee3659a-aa7a-466e-ad18-9eac9f625eb2","z":1,"attrs":{".marker-target":{"stroke":"#fe854f","fill":"#fe854f"},".connection":{"stroke":"#fe854f","stroke-width":4}}},{"type":"fsa.Arrow","smooth":true,"source":{"id":"9b9eab5d-10c5-4b81-86ff-454c77f7ced2"},"target":{"id":"9b9eab5d-10c5-4b81-86ff-454c77f7ced2"},"labels":[{"position":0.5,"attrs":{"text":{"text":"withdraw,deposit,interest","font-weight":"bold"}}}],"code":"","id":"49bffea5-1060-4b71-8a9e-05d35bc96b27","z":1,"vertices":[{"x":345,"y":75},{"x":420,"y":75}],"attrs":{".marker-target":{"stroke":"#fe854f","fill":"#fe854f"},".connection":{"stroke":"#fe854f","stroke-width":4}}},{"type":"fsa.Arrow","smooth":true,"source":{"id":"9b9eab5d-10c5-4b81-86ff-454c77f7ced2"},"target":{"id":"5fe4d720-0134-4835-8d64-c441f9ebd546"},"labels":[{"position":0.5,"attrs":{"text":{"text":"block","font-weight":"bold"}}}],"code":"","id":"a03077dc-00ad-4f30-8ed6-bb97909cb4da","z":1,"vertices":[],"attrs":{".marker-target":{"stroke":"#fe854f","fill":"#fe854f"},".connection":{"stroke":"#fe854f","stroke-width":4}}},{"type":"fsa.Arrow","smooth":true,"source":{"id":"5fe4d720-0134-4835-8d64-c441f9ebd546"},"target":{"id":"9b9eab5d-10c5-4b81-86ff-454c77f7ced2"},"labels":[{"position":0.5,"attrs":{"text":{"text":"unblock","font-weight":"bold"}}}],"code":"","id":"05b25b7c-5d68-4bef-80e8-12ad866d8e65","z":1,"vertices":[{"x":510,"y":345}],"attrs":{".marker-target":{"stroke":"#fe854f","fill":"#fe854f"},".connection":{"stroke":"#fe854f","stroke-width":4}}},{"type":"fsa.Arrow","smooth":true,"source":{"id":"9b9eab5d-10c5-4b81-86ff-454c77f7ced2"},"target":{"id":"557a2fc9-189f-4de3-ae8c-0b5103f55177"},"labels":[{"position":0.5,"attrs":{"text":{"text":"close","font-weight":"bold"}}}],"code":"","id":"579ee2a5-e17f-46f0-82a0-b8bd37750491","z":1,"vertices":[{"x":390,"y":390}],"attrs":{".marker-target":{"stroke":"#fe854f","fill":"#fe854f"},".connection":{"stroke":"#fe854f","stroke-width":4}}},{"type":"fsa.EndState","size":{"width":20,"height":20},"position":{"x":375,"y":450},"angle":0,"id":"557a2fc9-189f-4de3-ae8c-0b5103f55177","z":2,"attrs":{}},{"type":"fsa.State","size":{"width":100,"height":100},"position":{"x":315,"y":225},"angle":0,"id":"9b9eab5d-10c5-4b81-86ff-454c77f7ced2","z":3,"attrs":{"text":{"text":"opened"}}},{"type":"fsa.State","size":{"width":100,"height":100},"position":{"x":570,"y":225},"angle":0,"id":"5fe4d720-0134-4835-8d64-c441f9ebd546","z":3,"attrs":{"circle":{"r":"25"},"text":{"text":"blocked"},".":{"fill":"#f5400e"}}}]}],"fields":[{"fieldName":"accountNumber","value":"IBAN"},{"fieldName":"balance","value":"Money"}],"invariants":[{"fieldName":"mustBePositive","value":"invariant mustBePostive { this.balance >= EUR 50.00 }"}]}